valalgn/__init__.py
valalgn/asl/__init__.py
valalgn/asl/build.py
valalgn/asl/games.py
valalgn/asl/template.py
valalgn/sampling/__init__.py
valalgn/sampling/base.py
valalgn/sampling/template.py
valalgn-0.0.4.dist-info/LICENSE
valalgn-0.0.4.dist-info/METADATA
valalgn-0.0.4.dist-info/WHEEL
valalgn-0.0.4.dist-info/top_level.txt
valalgn-0.0.4.dist-info/RECORD
